MANIFEST.in
README.rst
setup.py
docs/HISTORY.txt
docs/LICENSE.GPL
docs/LICENSE.txt
ftw/__init__.py
ftw.zipexport.egg-info/PKG-INFO
ftw.zipexport.egg-info/SOURCES.txt
ftw.zipexport.egg-info/dependency_links.txt
ftw.zipexport.egg-info/entry_points.txt
ftw.zipexport.egg-info/namespace_packages.txt
ftw.zipexport.egg-info/not-zip-safe
ftw.zipexport.egg-info/requires.txt
ftw.zipexport.egg-info/top_level.txt
ftw/zipexport/__init__.py
ftw/zipexport/configure.zcml
ftw/zipexport/events.py
ftw/zipexport/generation.py
ftw/zipexport/interfaces.py
ftw/zipexport/testing.py
ftw/zipexport/utils.py
ftw/zipexport/zipfilestream.py
ftw/zipexport/browser/__init__.py
ftw/zipexport/browser/available.py
ftw/zipexport/browser/configure.zcml
ftw/zipexport/browser/zipexportview.py
ftw/zipexport/locales/ftw.zipexport.pot
ftw/zipexport/locales/de/LC_MESSAGES/ftw.zipexport.po
ftw/zipexport/locales/fr/LC_MESSAGES/ftw.zipexport.po
ftw/zipexport/profiles/default/actions.xml
ftw/zipexport/profiles/default/metadata.xml
ftw/zipexport/profiles/default/registry.xml
ftw/zipexport/profiles/documentaction/actions.xml
ftw/zipexport/profiles/documentaction/metadata.xml
ftw/zipexport/representations/__init__.py
ftw/zipexport/representations/archetypes.py
ftw/zipexport/representations/configure.zcml
ftw/zipexport/representations/dexterity.py
ftw/zipexport/representations/general.py
ftw/zipexport/tests/__init__.py
ftw/zipexport/tests/test_archetypes_image.py
ftw/zipexport/tests/test_dexterity_representation.py
ftw/zipexport/tests/test_dexterity_representation_namedfile.py
ftw/zipexport/tests/test_events.py
ftw/zipexport/tests/test_export.py
ftw/zipexport/tests/test_export_limitation.py
ftw/zipexport/tests/test_exportview.py
ftw/zipexport/tests/test_generaton.py
ftw/zipexport/tests/test_generic_setup.py
ftw/zipexport/tests/test_representation.py
ftw/zipexport/tests/test_utils.py
ftw/zipexport/tests/test_zipfilestream.py
ftw/zipexport/upgrades/__init__.py
ftw/zipexport/upgrades/configure.zcml
ftw/zipexport/upgrades/to1100.py
ftw/zipexport/upgrades/to1101.py
ftw/zipexport/upgrades/20170816165904_include_empty_folders_in_export/__init__.py
ftw/zipexport/upgrades/20170816165904_include_empty_folders_in_export/registry.xml
ftw/zipexport/upgrades/20170816165904_include_empty_folders_in_export/upgrade.py
