Metadata-Version: 2.1
Name: ftw.zipexport
Version: 1.6.3
Summary: Zip export for Plone
Home-page: https://github.com/4teamwork/ftw.zipexport
Author: 4teamwork AG
Author-email: mailto:info@4teamwork.ch
Maintainer: Lukas Knoepfel
License: GPL2
Keywords: ftw zip export
Platform: UNKNOWN
Classifier: Framework :: Plone
Classifier: Framework :: Zope2
Classifier: Framework :: Plone :: 4.3
Classifier: Framework :: Plone :: 5.1
Classifier: Programming Language :: Python
Classifier: Topic :: Software Development :: Libraries :: Python Modules
Provides-Extra: tests
